maser/__init__.py
maser/__main__.py
maser-0.1.0.dist-info/METADATA
maser-0.1.0.dist-info/WHEEL
maser-0.1.0.dist-info/RECORD
