Metadata-Version: 2.1
Name: maser
Version: 0.1.0
Summary: maser offers tools to handle low frequency radioastronomy data
Home-page: https://pypi.org/project/maser
License: CeCILL
Keywords: maser,data science,radioastronomy
Author: Baptiste CECCONI
Author-email: baptiste.cecconi@obspm.fr
Requires-Python: >=3.8,<4
Classifier: License :: Other/Proprietary License
Classifier: Programming Language :: Python :: 3
Classifier: Programming Language :: Python :: 3.8
Classifier: Programming Language :: Python :: 3.9
Classifier: Programming Language :: Python :: 3.10
Classifier: Programming Language :: Python :: 3.11
Classifier: Programming Language :: Python :: 3.12
Project-URL: Repository, https://github.com/maserlib/maser
